hashtree/__init__.py
hashtree/__main__.py
hashtree/cli.py
hashtree/clio.py
hashtree/exception_handler.py
hashtree/hash.py
hashtree/progress.py
hashtree/shell.py
hashtree/version.py
hashtree-1.1.6.dist-info/entry_points.txt
hashtree-1.1.6.dist-info/LICENSE
hashtree-1.1.6.dist-info/WHEEL
hashtree-1.1.6.dist-info/METADATA
hashtree-1.1.6.dist-info/RECORD
