Metadata-Version: 2.1
Name: hashtree
Version: 1.1.6
Summary: Top-level package for hashtree.
Keywords: hashtree
Author-email: Matt Krueger <mkrueger@rstms.net>
Classifier: Intended Audience :: Developers
Classifier: Natural Language :: English
Classifier: Programming Language :: Python :: 3
Classifier: Programming Language :: Python :: 3.10
Requires-Dist: click
Requires-Dist: tqdm
Requires-Dist: black ; extra == "dev"
Requires-Dist: bump2version ; extra == "dev"
Requires-Dist: coverage ; extra == "dev"
Requires-Dist: isort ; extra == "dev"
Requires-Dist: flake8 ; extra == "dev"
Requires-Dist: flake8-length ; extra == "dev"
Requires-Dist: pdbpp ; extra == "dev"
Requires-Dist: pytest ; extra == "dev"
Requires-Dist: pytest-datadir ; extra == "dev"
Requires-Dist: tox ; extra == "dev"
Requires-Dist: m2r2 ; extra == "docs"
Requires-Dist: sphinx ; extra == "docs"
Requires-Dist: sphinx-click ; extra == "docs"
Requires-Dist: pallets-sphinx-themes ; extra == "docs"
Project-URL: Home, https://github.com/rstms/hashtree
Provides-Extra: dev
Provides-Extra: docs
